{
  "$schema": "https://calm.finos.org/draft/1762/meta/calm-timeline.json",
  "$id": "https://calm.finos.org/draft/1762/prototype/arch-timeline/timeline.json",
  "current-moment": "insecure",
  "moments": [
    {
      "unique-id": "insecure",
      "name": "Initial design without security measures",
      "description": "This moment represents the architecture before any security measures were implemented, for POC purposes.",
      "details": {
        "detail": "https://calm.finos.org/draft/1762/prototype/arch-timeline/arch-insecure.json",
        "detail-type": "architecture"
      },
      "valid-from": "2024-06-01"
    },
    {
      "unique-id": "secure",
      "name": "Enhanced design with security measures",
      "details": {
        "detail": "https://calm.finos.org/draft/1762/prototype/arch-timeline/timeline-baby.json",
        "detail-type": "sub-timeline"
      },
      "adrs": [
        "https://calm.finos.org/draft/1762/prototype/adrs/add-security.md"
      ]
    }
  ]
}